ocopy/__init__.py
ocopy/copy.py
ocopy/file_info.py
ocopy/hash.py
ocopy/mhl.py
ocopy/progress.py
ocopy/utils.py
ocopy/cli/__init__.py
ocopy/cli/ocopy.py
tests/__init__.py
tests/test_copy.py
ocopy-0.2.4.dist-info/LICENSE
ocopy-0.2.4.dist-info/METADATA
ocopy-0.2.4.dist-info/WHEEL
ocopy-0.2.4.dist-info/entry_points.txt
ocopy-0.2.4.dist-info/top_level.txt
ocopy-0.2.4.dist-info/RECORD
